datehandling/__init__.py
datehandling/fechas.py
datehandling/listas.py
datehandling-0.1.1.dist-info/LICENCE.txt
datehandling-0.1.1.dist-info/METADATA
datehandling-0.1.1.dist-info/WHEEL
datehandling-0.1.1.dist-info/top_level.txt
datehandling-0.1.1.dist-info/RECORD
