Metadata-Version: 2.1
Name: datehandling
Version: 0.1.1
Summary: library for handling dates
Home-page: 
Author: Daniel Chaparro
Author-email: daniel.chaparro.ds@gmail.com
License-File: LICENCE.txt
